researchpy/__init__.py
researchpy/anova.py
researchpy/basic_stats.py
researchpy/correlation.py
researchpy/crosstab.py
researchpy/difference_test.py
researchpy/model.py
researchpy/ols.py
researchpy/predict.py
researchpy/setup.py
researchpy/signrank.py
researchpy/summary.py
researchpy/ttest.py
researchpy/utility.py
researchpy/version.py
researchpy-0.3.6.dist-info/LICENSE.txt
researchpy-0.3.6.dist-info/METADATA
researchpy-0.3.6.dist-info/WHEEL
researchpy-0.3.6.dist-info/top_level.txt
researchpy-0.3.6.dist-info/RECORD
