Metadata-Version: 2.1
Name: researchpy
Version: 0.3.6
Summary: Researchpy produces Pandas DataFrames that contain relevant statistical testing information that is commonly required for academic research.
Author-email: Corey Bryant <CoreyBryant10@gmail.com>
Maintainer-email: Corey Bryant <CoreyBryant10@gmail.com>
Project-URL: Homepage, https://researchpy.readthedocs.io/
Project-URL: Documentation, https://researchpy.readthedocs.io/
Project-URL: Repository, https://github.com/researchpy/researchpy.git
Keywords: researchpy,statistics
Classifier: Programming Language :: Python :: 3
Classifier: License :: OSI Approved :: MIT License
Classifier: Operating System :: OS Independent
Requires-Python: >=3.7
License-File: LICENSE.txt
Requires-Dist: scipy
Requires-Dist: numpy
Requires-Dist: pandas
Requires-Dist: statsmodels
Requires-Dist: patsy
